clld_etymology_plugin/__init__.py
clld_etymology_plugin/adapters.py
clld_etymology_plugin/datatables.py
clld_etymology_plugin/interfaces.py
clld_etymology_plugin/maps.py
clld_etymology_plugin/models.py
clld_etymology_plugin/static/alignment.css
clld_etymology_plugin/static/alignment.js
clld_etymology_plugin/templates/borrowing/detail_html.mako
clld_etymology_plugin/templates/borrowing/index_html.mako
clld_etymology_plugin/templates/cognate/detail_html.mako
clld_etymology_plugin/templates/cognate/index_html.mako
clld_etymology_plugin/templates/cognateset/cogset_material.mako
clld_etymology_plugin/templates/cognateset/detail_html.mako
clld_etymology_plugin/templates/cognateset/index_html.mako
clld_etymology_plugin/util.py
clld_etymology_plugin-0.1.2.dist-info/LICENSE
clld_etymology_plugin-0.1.2.dist-info/METADATA
clld_etymology_plugin-0.1.2.dist-info/WHEEL
clld_etymology_plugin-0.1.2.dist-info/entry_points.txt
clld_etymology_plugin-0.1.2.dist-info/RECORD
